pynrl1/downlink/__init__.py
pynrl1/downlink/nrPBCH.py
pynrl1/downlink/nrPBCHDMRS.py
pynrl1/downlink/nrPBCHDMRSIndices.py
pynrl1/downlink/nrPBCHIndices.py
pynrl1/downlink/nrPDSCHDMRS.py
pynrl1/downlink/nrPDSCHDMRSIndices.py
pynrl1/downlink/nrPSS.py
pynrl1/downlink/nrPSSIndices.py
pynrl1/downlink/nrSSS.py
pynrl1/downlink/nrSSSIndices.py
pynrl1/util/__init__.py
pynrl1/util/nrCarrierConfig.py
pynrl1/util/nrNumerologyConfig.py
pynrl1/util/nrPDSCHConfig.py
pynrl1/util/nrPRBS.py
pynrl1/util/nrSymbolModulate.py
pynrl1-0.0.6.dist-info/LICENSE
pynrl1-0.0.6.dist-info/METADATA
pynrl1-0.0.6.dist-info/WHEEL
pynrl1-0.0.6.dist-info/top_level.txt
pynrl1-0.0.6.dist-info/RECORD
