Metadata-Version: 2.1
Name: pynrl1
Version: 0.0.6
Summary: L1 NR 3GPP Python implementation
Home-page: https://github.com/vborchsh/pynrl1
Download-URL: https://github.com/vborchsh/pynrl1/tarball/master
Author: Vladislav Borshch
Author-email: borchsh.vn@mail.com
License: MIT
Project-URL: Bug Tracker, https://github.com/vborchsh/pynrl1/issues
Project-URL: Source Code, https://github.com/vborchsh/pynrl1
Keywords: l1,3gpp,python,5g,nr
Platform: any
Classifier: Development Status :: 3 - Alpha
Classifier: License :: OSI Approved :: MIT License
Classifier: Operating System :: OS Independent
Classifier: Programming Language :: Python :: 3
Classifier: Topic :: Scientific/Engineering :: Electronic Design Automation (EDA)
Requires-Python: >=3.6
License-File: LICENSE
Requires-Dist: numpy (>=1.21.0)
Provides-Extra: test
Requires-Dist: pytest ; extra == 'test'
